{
  "stem": "vol2_p0820",
  "timestamp": "2026-04-20T06:54:58.820757Z",
  "tier_filter": [
    "cosmetic",
    "grammatical",
    "body-meaning",
    "apparatus-meaning"
  ],
  "applied": [],
  "deferred": [
    {
      "section": "BODY",
      "location": "Judith XI 1",
      "current": "ὅστις ᾑρέτικεν δουλεύειν",
      "correct": "ὅστις ἡρέτικεν δουλεύειν",
      "severity": "cosmetic",
      "category": "accent",
      "confidence": "high",
      "note": "Printed form has smooth-breathed/acute ἡρέτικεν, not ᾑρέτικεν.",
      "_defer_reason": "match=no-match",
      "_tier": "cosmetic"
    },
    {
      "section": "BODY",
      "location": "Judith XI 5",
      "current": "5καὶ εἶπεν",
      "correct": "καὶ εἶπεν",
      "severity": "cosmetic",
      "category": "line-number-captured-as-verse",
      "confidence": "high",
      "note": "Leading verse number 5 is not part of the text.",
      "_defer_reason": "match=no-match",
      "_tier": "cosmetic"
    },
    {
      "section": "BODY",
      "location": "Judith XI 8",
      "current": "8ἠκούσαμεν",
      "correct": "ἠκούσαμεν",
      "severity": "cosmetic",
      "category": "line-number-captured-as-verse",
      "confidence": "high",
      "note": "Leading verse number 8 is not part of the text.",
      "_defer_reason": "match=no-match",
      "_tier": "cosmetic"
    },
    {
      "section": "BODY",
      "location": "Judith XI 10",
      "current": "ἐκδικαται",
      "correct": "ἐκδικάται",
      "severity": "cosmetic",
      "category": "accent",
      "confidence": "high",
      "note": "Accent missing in transcript.",
      "_defer_reason": "match=no-match",
      "_tier": "cosmetic"
    },
    {
      "section": "BODY",
      "location": "Judith XI 11",
      "current": "11καὶ νῦν",
      "correct": "καὶ νῦν",
      "severity": "cosmetic",
      "category": "line-number-captured-as-verse",
      "confidence": "high",
      "note": "Leading verse number 11 is not part of the text.",
      "_defer_reason": "match=no-match",
      "_tier": "cosmetic"
    },
    {
      "section": "BODY",
      "location": "Judith XI 2",
      "current": "2καὶ νῦν",
      "correct": "καὶ νῦν",
      "severity": "cosmetic",
      "category": "line-number-captured-as-verse",
      "confidence": "high",
      "note": "Leading verse number 2 is not part of the text.",
      "_defer_reason": "match=no-match",
      "_tier": "cosmetic"
    },
    {
      "section": "BODY",
      "location": "Judith XI 3",
      "current": "3καὶ νῦν",
      "correct": "καὶ νῦν",
      "severity": "cosmetic",
      "category": "line-number-captured-as-verse",
      "confidence": "high",
      "note": "Leading verse number 3 is not part of the text.",
      "_defer_reason": "match=no-match",
      "_tier": "cosmetic"
    },
    {
      "section": "BODY",
      "location": "Judith XI 6",
      "current": "6καὶ ἐὰν",
      "correct": "καὶ ἐὰν",
      "severity": "cosmetic",
      "category": "line-number-captured-as-verse",
      "confidence": "high",
      "note": "Leading verse number 6 is not part of the text.",
      "_defer_reason": "match=no-match",
      "_tier": "cosmetic"
    },
    {
      "section": "BODY",
      "location": "Judith XI 9",
      "current": "9καὶ νῦν",
      "correct": "καὶ νῦν",
      "severity": "cosmetic",
      "category": "line-number-captured-as-verse",
      "confidence": "high",
      "note": "Leading verse number 9 is not part of the text.",
      "_defer_reason": "match=no-match",
      "_tier": "cosmetic"
    },
    {
      "section": "BODY",
      "location": "Judith XI 4",
      "current": "4οὐ γὰρ",
      "correct": "οὐ γὰρ",
      "severity": "cosmetic",
      "category": "line-number-captured-as-verse",
      "confidence": "high",
      "note": "Leading verse number 4 is not part of the text.",
      "_defer_reason": "match=no-match",
      "_tier": "cosmetic"
    },
    {
      "section": "BODY",
      "location": "Judith XI 7",
      "current": "7ζῇ γὰρ",
      "correct": "ζῇ γὰρ",
      "severity": "cosmetic",
      "category": "line-number-captured-as-verse",
      "confidence": "high",
      "note": "Leading verse number 7 is not part of the text.",
      "_defer_reason": "match=no-match",
      "_tier": "cosmetic"
    },
    {
      "section": "BODY",
      "location": "Judith XI 10",
      "current": "10διό,",
      "correct": "διό,",
      "severity": "cosmetic",
      "category": "line-number-captured-as-verse",
      "confidence": "high",
      "note": "Leading verse number 10 is not part of the text.",
      "_defer_reason": "match=no-match",
      "_tier": "cosmetic"
    }
  ]
}