{
  "stem": "vol2_p0699",
  "timestamp": "2026-04-20T06:54:58.779640Z",
  "tier_filter": [
    "cosmetic",
    "grammatical",
    "body-meaning",
    "apparatus-meaning"
  ],
  "applied": [],
  "deferred": [
    {
      "section": "APPARATUS",
      "location": "line for 30",
      "current": "αναγγελει ℵAC (-λει)+σου C",
      "correct": "αναγγελει ℵAC (-λει)+σου C |",
      "severity": "cosmetic",
      "category": "punctuation",
      "confidence": "medium",
      "note": "A separator follows C before the next reading.",
      "_defer_reason": "confidence=medium",
      "_tier": "cosmetic"
    },
    {
      "section": "APPARATUS",
      "location": "line for 26",
      "current": "συνκε-\nκυφως Bab",
      "correct": "συγκε-\nκυφως Bab",
      "severity": "cosmetic",
      "category": "missing-letter",
      "confidence": "high",
      "note": "Apparatus also has gamma in the lemma: συγκε-κυφως.",
      "_defer_reason": "match=no-match",
      "_tier": "cosmetic"
    },
    {
      "section": "APPARATUS",
      "location": "line for 27",
      "current": "(συνκ. BabAC)]",
      "correct": "(συγκ. BabAC)]",
      "severity": "cosmetic",
      "category": "missing-letter",
      "confidence": "high",
      "note": "Abbreviation includes gamma: συγκ.",
      "_defer_reason": "match=no-match",
      "_tier": "cosmetic"
    },
    {
      "section": "APPARATUS",
      "location": "line for 24",
      "current": "κρισ-\nσων C",
      "correct": "κρισ-\nσων C |",
      "severity": "cosmetic",
      "category": "punctuation",
      "confidence": "medium",
      "note": "A vertical separator follows C before the next variant.",
      "_defer_reason": "confidence=medium",
      "_tier": "cosmetic"
    },
    {
      "section": "BODY",
      "location": "Sir 20:26",
      "current": "συνκεκυφὼς",
      "correct": "συγκεκυφὼς",
      "severity": "cosmetic",
      "category": "missing-letter",
      "confidence": "high",
      "note": "Printed text has gamma: συγκεκυφώς.",
      "_defer_reason": "match=no-match",
      "_tier": "cosmetic"
    },
    {
      "section": "BODY",
      "location": "Sir 20:27",
      "current": "συνκύφων",
      "correct": "συγκύφων",
      "severity": "cosmetic",
      "category": "missing-letter",
      "confidence": "high",
      "note": "Printed text reads συγκύφων.",
      "_defer_reason": "match=no-match",
      "_tier": "cosmetic"
    },
    {
      "section": "APPARATUS",
      "location": "line for 23",
      "current": "ℵ*eidi",
      "correct": "ℵ*vid",
      "severity": "cosmetic",
      "category": "siglum-decode",
      "confidence": "high",
      "note": "Standard siglum is vid, and the page clearly reads vid.",
      "_defer_reason": "match=no-match",
      "_tier": "cosmetic"
    },
    {
      "section": "APPARATUS",
      "location": "line for 16",
      "current": "Babℵ",
      "correct": "Bab B",
      "severity": "cosmetic",
      "category": "siglum-decode",
      "confidence": "high",
      "note": "Final siglum is Latin B, not ℵ.",
      "_defer_reason": "match=no-match",
      "_tier": "cosmetic"
    },
    {
      "section": "APPARATUS",
      "location": "line for 29",
      "current": "ἀπο 1°] pr [κ]αι C*",
      "correct": "ἀπο 1°] pr [κ] C*",
      "severity": "meaning-altering",
      "category": "extra-letter",
      "confidence": "high",
      "note": "Apparatus reads pr [κ] C*, not [κ]αι C*.",
      "_defer_reason": "match=no-match",
      "_tier": "apparatus-meaning"
    },
    {
      "section": "APPARATUS",
      "location": "line for 20",
      "current": "φο-",
      "correct": "φοβος] παρὰ C | ποιησεις ACa",
      "severity": "meaning-altering",
      "category": "missing-phrase",
      "confidence": "high",
      "note": "The remainder of the apparatus line after the carry-over hyphen is omitted.",
      "_defer_reason": "match=no-match",
      "_tier": "apparatus-meaning"
    }
  ]
}