{
  "stem": "vol2_p0623",
  "timestamp": "2026-04-20T06:54:58.748997Z",
  "tier_filter": [
    "cosmetic",
    "grammatical",
    "body-meaning",
    "apparatus-meaning"
  ],
  "applied": [
    {
      "section": "BODY",
      "location": "Wis 2:12",
      "current": "12ἐνεδρεύσωμεν δὲ τὸν δίκαιον, ὅτι δύσχρηστος ἡμῖν ἐστίν,",
      "correct": "ἐνεδρεύσωμεν δὲ τὸν δίκαιον, ὅτι δύσχρηστος ἡμῖν ἐστίν,",
      "severity": "cosmetic",
      "category": "line-number-captured-as-verse",
      "confidence": "high",
      "note": "Left-margin verse number captured into body.",
      "_tier": "cosmetic"
    },
    {
      "section": "BODY",
      "location": "Wis 2:9",
      "current": "9μηδεὶς ἡμῶν ἄμοιρος ἔστω τῆς ἡμετέρας ἀγερωχίας,",
      "correct": "μηδεὶς ἡμῶν ἄμοιρος ἔστω τῆς ἡμετέρας ἀγερωχίας,",
      "severity": "cosmetic",
      "category": "line-number-captured-as-verse",
      "confidence": "high",
      "note": "Left-margin verse number captured into body.",
      "_tier": "cosmetic"
    },
    {
      "section": "BODY",
      "location": "Wis 2:11",
      "current": "11ἔστω δὲ ἡμῶν ἡ ἰσχὺς νόμος τῆς δικαιοσύνης,",
      "correct": "ἔστω δὲ ἡμῶν ἡ ἰσχὺς νόμος τῆς δικαιοσύνης,",
      "severity": "cosmetic",
      "category": "line-number-captured-as-verse",
      "confidence": "high",
      "note": "Left-margin verse number captured into body.",
      "_tier": "cosmetic"
    },
    {
      "section": "BODY",
      "location": "Wis 2:6",
      "current": "6δεῦτε οὖν καὶ ἀπολαύσωμεν τῶν ὄντων ἀγαθῶν,",
      "correct": "δεῦτε οὖν καὶ ἀπολαύσωμεν τῶν ὄντων ἀγαθῶν,",
      "severity": "cosmetic",
      "category": "line-number-captured-as-verse",
      "confidence": "high",
      "note": "Left-margin verse number captured into body.",
      "_tier": "cosmetic"
    },
    {
      "section": "BODY",
      "location": "Wis 2:8",
      "current": "8στεψώμεθα ῥόδων κάλυξιν πρὶν ἢ μαρανθῆναι·",
      "correct": "στεψώμεθα ῥόδων κάλυξιν πρὶν ἢ μαρανθῆναι·",
      "severity": "cosmetic",
      "category": "line-number-captured-as-verse",
      "confidence": "high",
      "note": "Left-margin verse number captured into body.",
      "_tier": "cosmetic"
    },
    {
      "section": "BODY",
      "location": "Wis 2:4, first line on page",
      "current": "4καὶ τὸ ὄνομα ἡμῶν ἐπιλησθήσεται ἐν χρόνῳ,",
      "correct": "καὶ τὸ ὄνομα ἡμῶν ἐπιλησθήσεται ἐν χρόνῳ,",
      "severity": "cosmetic",
      "category": "line-number-captured-as-verse",
      "confidence": "high",
      "note": "The left-margin verse number 4 has been captured into the body text.",
      "_tier": "cosmetic"
    },
    {
      "section": "BODY",
      "location": "Wis 2:14",
      "current": "14ἐγένετο ἡμῖν εἰς ἔλεγχον ἐννοιῶν ἡμῶν·",
      "correct": "ἐγένετο ἡμῖν εἰς ἔλεγχον ἐννοιῶν ἡμῶν·",
      "severity": "cosmetic",
      "category": "line-number-captured-as-verse",
      "confidence": "high",
      "note": "Left-margin verse number captured into body.",
      "_tier": "cosmetic"
    },
    {
      "section": "BODY",
      "location": "Wis 2:7",
      "current": "7οἴνου πολυτελοῦς καὶ μύρων πλησθῶμεν,",
      "correct": "οἴνου πολυτελοῦς καὶ μύρων πλησθῶμεν,",
      "severity": "cosmetic",
      "category": "line-number-captured-as-verse",
      "confidence": "high",
      "note": "Left-margin verse number captured into body.",
      "_tier": "cosmetic"
    },
    {
      "section": "BODY",
      "location": "Wis 2:10",
      "current": "10καταδυναστεύσωμεν πένητα δίκαιον,",
      "correct": "καταδυναστεύσωμεν πένητα δίκαιον,",
      "severity": "cosmetic",
      "category": "line-number-captured-as-verse",
      "confidence": "high",
      "note": "Left-margin verse number captured into body.",
      "_tier": "cosmetic"
    },
    {
      "section": "BODY",
      "location": "Wis 2:13",
      "current": "13ἐπαγγέλλεται γνῶσιν ἔχειν θεοῦ,",
      "correct": "ἐπαγγέλλεται γνῶσιν ἔχειν θεοῦ,",
      "severity": "cosmetic",
      "category": "line-number-captured-as-verse",
      "confidence": "high",
      "note": "Left-margin verse number captured into body.",
      "_tier": "cosmetic"
    },
    {
      "section": "BODY",
      "location": "Wis 2:5",
      "current": "5σκιᾶς γὰρ πάροδος ὁ βίος ἡμῶν,",
      "correct": "σκιᾶς γὰρ πάροδος ὁ βίος ἡμῶν,",
      "severity": "cosmetic",
      "category": "line-number-captured-as-verse",
      "confidence": "high",
      "note": "Left-margin verse number captured into body.",
      "_tier": "cosmetic"
    },
    {
      "section": "APPARATUS",
      "location": "apparatus, v.7",
      "current": "7 ημας] με ℵ* (ημ.. ℵc.a) |",
      "correct": "7 ημας] με ℵ* (ημ.. ℵc.a) A |",
      "severity": "cosmetic",
      "category": "siglum-decode",
      "confidence": "high",
      "note": "Apparatus omits the final siglum A after the parenthesis.",
      "_tier": "cosmetic"
    },
    {
      "section": "APPARATUS",
      "location": "apparatus, lemma for v.5",
      "current": "5 βιος B*Aa] καιρος BabℵA*",
      "correct": "5 βιος B*Aa] καιρος BabℵA",
      "severity": "cosmetic",
      "category": "siglum-decode",
      "confidence": "high",
      "note": "The final siglum is A, not A*.",
      "_tier": "cosmetic"
    },
    {
      "section": "APPARATUS",
      "location": "apparatus, v.9",
      "current": "9 εστω] εστε ℵ |",
      "correct": "9 εστω] εστε ℵA |",
      "severity": "cosmetic",
      "category": "siglum-decode",
      "confidence": "high",
      "note": "Both ℵ and A support εστε.",
      "_tier": "cosmetic"
    }
  ],
  "deferred": [
    {
      "section": "APPARATUS",
      "location": "apparatus, v.6",
      "current": "6 om\nκαι ι̣ο A",
      "correct": "6 om\nκαι ι A",
      "severity": "cosmetic",
      "category": "other",
      "confidence": "medium",
      "note": "The reading is ι A; the extra dotted omicron is not present.",
      "_defer_reason": "confidence=medium",
      "_tier": "cosmetic"
    }
  ]
}