{
  "stem": "vol2_p0861",
  "timestamp": "2026-04-20T03:35:21.422953Z",
  "tier_filter": [
    "cosmetic",
    "grammatical",
    "body-meaning",
    "apparatus-meaning"
  ],
  "applied": [
    {
      "section": "BODY",
      "location": "Tobit 13:8",
      "current": "8λεγετώσαν πάντες καὶ ἐξομολογείσθωσαν αὐτῷ ἐν Ἱεροσολύμοις.",
      "correct": "8λεγετέτωσαν πάντες καὶ ἐξομολογείσθωσαν αὐτῷ ἐν Ἱεροσολύμοις.",
      "severity": "grammatical",
      "category": "missing-letter",
      "confidence": "high",
      "note": "Printed text clearly has λεγετέτωσαν, not λεγετώσαν.",
      "_tier": "grammatical"
    },
    {
      "section": "APPARATUS",
      "location": "apparatus line for 13",
      "current": "13τότε πορευθήσῃ καὶ ἀγαλλιάσαι ἐπὶ τοῖς υἱοῖς τῶν δικαίων,",
      "correct": "13τότε πορευθήσῃ καὶ ἀγαλλιάσει ἐπὶ τοῖς υἱοῖς τῶν δικαίων,",
      "severity": "grammatical",
      "category": "missing-letter",
      "confidence": "high",
      "note": "Apparatus text reads ἀγαλλιάσει, not ἀγαλλιάσαι.",
      "_tier": "grammatical"
    },
    {
      "section": "APPARATUS",
      "location": "apparatus line for 12",
      "current": "ἐπικατάρατοι πάντες οἱ ἐροῦντές σοι σκληρόν,",
      "correct": "ἐπικατάρατοι πάντες οἱ ἐροῦντές σοι λόγον σκληρόν,",
      "severity": "meaning-altering",
      "category": "missing-letter",
      "confidence": "high",
      "note": "The word λόγον is present in the apparatus and omitted in the transcription.",
      "_tier": "apparatus-meaning"
    }
  ],
  "deferred": [
    {
      "section": "BODY",
      "location": "Tobit 13:11",
      "current": "γενεαὶ γενεῶν δώσουσίν σοι ἀγαλλίαμα.",
      "correct": "γενεαὶ γενεῶν δώσουσίν σοι ἀγαλλίαμα.",
      "severity": "cosmetic",
      "category": "accent",
      "confidence": "high",
      "note": "Acute in print is on the final syllable of ἀγαλλίαμα, not ἀγαλλίαμα.",
      "_defer_reason": "no-op",
      "_tier": "cosmetic"
    },
    {
      "section": "APPARATUS",
      "location": "critical note 13",
      "current": "13 χαρητι] B* A (χαρηθι Bab)",
      "correct": "13 χαρητι] B* A (χαρηθι Bᵃᵇ)",
      "severity": "cosmetic",
      "category": "siglum-decode",
      "confidence": "medium",
      "note": "Superscript ab after B is printed as a siglum, not plain Bab.",
      "_defer_reason": "confidence=medium",
      "_tier": "cosmetic"
    }
  ]
}