{
  "stem": "vol2_p0770",
  "timestamp": "2026-04-20T06:54:58.803571Z",
  "tier_filter": [
    "cosmetic",
    "grammatical",
    "body-meaning",
    "apparatus-meaning"
  ],
  "applied": [],
  "deferred": [
    {
      "section": "BODY",
      "location": "Sir 51:16 line start",
      "current": "(21) 16 16ἔκλινα ὀλίγον τὸ οὖς μου καὶ ἐδεξάμην,",
      "correct": "(21) 16 ἔκλινα ὀλίγον τὸ οὖς μου καὶ ἐδεξάμην,",
      "severity": "cosmetic",
      "category": "line-number-captured-as-verse",
      "confidence": "high",
      "note": "Duplicated verse number 16; only one is present in the image.",
      "_defer_reason": "match=no-match",
      "_tier": "cosmetic"
    },
    {
      "section": "BODY",
      "location": "Sir 51:13 line start",
      "current": "(18) 13 13Ἔτι ὢν νεώτερος πρὶν ἢ πλανηθῆναί με,",
      "correct": "(18) 13 Ἔτι ὢν νεώτερος πρὶν ἢ πλανηθῆναί με,",
      "severity": "cosmetic",
      "category": "line-number-captured-as-verse",
      "confidence": "high",
      "note": "The verse number 13 has been duplicated; the image shows a single 13 in the margin/body marker.",
      "_defer_reason": "match=no-match",
      "_tier": "cosmetic"
    },
    {
      "section": "APPARATUS",
      "location": "apparatus line 8, variant for ἐξέλῃ",
      "current": "8 om καὶ 1° ℵ* (hab γ κς᾽) | ἐξέλη] ἐξαιρη ℵA",
      "correct": "8 om καὶ 1° ℵ* (hab γ κς᾽) | ἐξέλῃ] ἐξαίρῃ ℵA",
      "severity": "cosmetic",
      "category": "accent",
      "confidence": "high",
      "note": "The apparatus prints accents on both lemma and variant here.",
      "_defer_reason": "match=no-match",
      "_tier": "cosmetic"
    },
    {
      "section": "BODY",
      "location": "Sir 51:18 line start",
      "current": "(24) 18 18διενοήθην γὰρ τοῦ ποιῆσαι αὐτήν,",
      "correct": "(24) 18 διενοήθην γὰρ τοῦ ποιῆσαι αὐτήν,",
      "severity": "cosmetic",
      "category": "line-number-captured-as-verse",
      "confidence": "high",
      "note": "Duplicated verse number 18; only one is present in the image.",
      "_defer_reason": "match=no-match",
      "_tier": "cosmetic"
    },
    {
      "section": "BODY",
      "location": "Sir 51:14 line start",
      "current": "(19) 14 14ἔναντι ναοῦ ἠξίουν περὶ αὐτῆς,",
      "correct": "(19) 14 ἔναντι ναοῦ ἠξίουν περὶ αὐτῆς,",
      "severity": "cosmetic",
      "category": "line-number-captured-as-verse",
      "confidence": "high",
      "note": "Duplicated verse number 14; only one is present in the image.",
      "_defer_reason": "match=no-match",
      "_tier": "cosmetic"
    },
    {
      "section": "APPARATUS",
      "location": "apparatus line 13, variant for πλανηθῆναι",
      "current": "13 πλανηθηναι B*vid (πλανηθῆ Bᵇ)",
      "correct": "13 πλανη θη- ναι B*vid (πλανηθῆ Bᵇ)",
      "severity": "cosmetic",
      "category": "punctuation",
      "confidence": "medium",
      "note": "Printed with line-break hyphenation in the image; transcript has normalized it. If preserving exact apparatus typography is required, this differs.",
      "_defer_reason": "confidence=medium",
      "_tier": "cosmetic"
    },
    {
      "section": "APPARATUS",
      "location": "apparatus line 9, variant for ἱκετείαν",
      "current": "9 ανυψωσεν ℵ* | επι] απο ℵA | γην] γης BᵇA*ℵA | ἱκετειαν] Bᵃᵇ | ὑπερ] απο A | θανατου] αθανατου A",
      "correct": "9 ανυψωσεν ℵ* | επι] απο ℵA | γην] γης BᵃᵇA*ℵA | ἱκετειαν] ἱκεσιαν Bᵃᵇ | ὑπερ] απο A | θανατου] αθανατου A",
      "severity": "meaning-altering",
      "category": "missing-phrase",
      "confidence": "high",
      "note": "The siglum Bᵃᵇ belongs with γης, and the variant for ἱκετειαν is ἱκεσιαν before Bᵃᵇ.",
      "_defer_reason": "match=no-match",
      "_tier": "apparatus-meaning"
    },
    {
      "section": "APPARATUS",
      "location": "apparatus line 8 continuation",
      "current": "(ἐξερη) A | ἐθνων] χθρων ℵA",
      "correct": "(ἐξερῇ) A | ἐθνων] ἐχθρων ℵA",
      "severity": "meaning-altering",
      "category": "missing-letter",
      "confidence": "high",
      "note": "The parenthetical form ends with eta-iota, and χθρων in the transcript is missing initial epsilon: image reads ἐχθρων.",
      "_defer_reason": "match=no-match",
      "_tier": "apparatus-meaning"
    },
    {
      "section": "APPARATUS",
      "location": "apparatus line 15, variant for εὐφράνθη",
      "current": "εὐφράνθη A",
      "correct": "ηυφράνθη A",
      "severity": "meaning-altering",
      "category": "missing-letter",
      "confidence": "high",
      "note": "The apparatus variant begins with eta, not epsilon: image reads ηυφράνθη A.",
      "_defer_reason": "match=no-match",
      "_tier": "apparatus-meaning"
    }
  ]
}