{
  "stem": "vol2_p0641",
  "timestamp": "2026-04-20T03:35:21.178847Z",
  "tier_filter": [
    "cosmetic",
    "grammatical",
    "body-meaning",
    "apparatus-meaning"
  ],
  "applied": [
    {
      "section": "APPARATUS",
      "location": "Wis 11:25",
      "current": "αν τι] pr εν (? εναντι) ℵ* improb εν ℵc.a | αν τις C",
      "correct": "αν τι] pr εν (? εναντι) ℵ* improb εν ℵc.a | αν τι C",
      "severity": "cosmetic",
      "category": "extra-letter",
      "confidence": "high",
      "note": "Apparatus gives αν τι C, matching the printed line.",
      "_tier": "cosmetic"
    },
    {
      "section": "APPARATUS",
      "location": "Wis 12:2",
      "current": "κακιας] +αυτου ℵ* (improb αυτου ℵc.a)",
      "correct": "κακιας] + αυτου ℵ* (improb αυτου ℵc.a)",
      "severity": "cosmetic",
      "category": "punctuation",
      "confidence": "high",
      "note": "Space after plus sign in print.",
      "_tier": "cosmetic"
    },
    {
      "section": "BODY",
      "location": "Wis 11:20",
      "current": "ἐνὶ πνεύματι πεσεῖν ἐδύναντο",
      "correct": "ἐνὶ πνεύματι πεσεῖν· ἐδύναντο",
      "severity": "cosmetic",
      "category": "punctuation",
      "confidence": "high",
      "note": "Middle point after πεσεῖν is present in the print.",
      "_tier": "cosmetic"
    },
    {
      "section": "APPARATUS",
      "location": "Wis 11:19",
      "current": "συνεκτρῖψαι ἐκτρῖψαι ℵc.aAC",
      "correct": "συνεκτριψαι εκτριψαι ℵc.aAC",
      "severity": "cosmetic",
      "category": "accent",
      "confidence": "high",
      "note": "Apparatus forms are printed without accents.",
      "_tier": "cosmetic"
    },
    {
      "section": "APPARATUS",
      "location": "Wis 11:20",
      "current": "om δικης ℵ* (hab ℵc.a)",
      "correct": "om της δικης ℵ* (hab ℵc.a)",
      "severity": "cosmetic",
      "category": "missing-letter",
      "confidence": "high",
      "note": "Article της is present in apparatus.",
      "_tier": "cosmetic"
    },
    {
      "section": "APPARATUS",
      "location": "Wis 11:22",
      "current": "πλαστιγγων παστ. B*",
      "correct": "πλαστιγγων] παστ. B*",
      "severity": "cosmetic",
      "category": "punctuation",
      "confidence": "high",
      "note": "Closing bracket after lemma is present.",
      "_tier": "cosmetic"
    },
    {
      "section": "APPARATUS",
      "location": "Wis 11:26",
      "current": "εστιν] +παντα ACvid",
      "correct": "εστιν] + παντα ACvid",
      "severity": "cosmetic",
      "category": "punctuation",
      "confidence": "high",
      "note": "Space after plus sign in print.",
      "_tier": "cosmetic"
    },
    {
      "section": "APPARATUS",
      "location": "Wis 12:3",
      "current": "παλαιους] παλαι. ℵ",
      "correct": "παλαιους] παλαι ℵ",
      "severity": "cosmetic",
      "category": "punctuation",
      "confidence": "high",
      "note": "No period after παλαι in the printed apparatus.",
      "_tier": "cosmetic"
    },
    {
      "section": "APPARATUS",
      "location": "Wis 12:1",
      "current": "πασιν]\nπαστι ℵ",
      "correct": "πασιν]\nπασι ℵ",
      "severity": "cosmetic",
      "category": "extra-letter",
      "confidence": "high",
      "note": "Apparatus reads πασι ℵ, not παστι.",
      "_tier": "cosmetic"
    },
    {
      "section": "APPARATUS",
      "location": "Wis 11:22",
      "current": "ορθρινην C",
      "correct": "ορθρινη C",
      "severity": "cosmetic",
      "category": "extra-letter",
      "confidence": "high",
      "note": "Apparatus reads ορθρινη, not accusative ορθρινην.",
      "_tier": "cosmetic"
    },
    {
      "section": "APPARATUS",
      "location": "Wis 11:19",
      "current": "ἐδύνατο A",
      "correct": "ἐδυνατο A",
      "severity": "cosmetic",
      "category": "accent",
      "confidence": "high",
      "note": "Apparatus prints unaccented ἐδυνατο.",
      "_tier": "cosmetic"
    },
    {
      "section": "APPARATUS",
      "location": "Wis 12:5",
      "current": "φονεας C",
      "correct": "φονεας C |",
      "severity": "cosmetic",
      "category": "punctuation",
      "confidence": "high",
      "note": "A separator bar follows C before the next variant.",
      "_tier": "cosmetic"
    },
    {
      "section": "BODY",
      "location": "Wis 12:3",
      "current": "Καὶ γὰρ",
      "correct": "καὶ γὰρ",
      "severity": "cosmetic",
      "category": "case",
      "confidence": "high",
      "note": "New section begins with lowercase καὶ, not capitalized.",
      "_tier": "cosmetic"
    },
    {
      "section": "BODY",
      "location": "Wis 11:24",
      "current": "βδελύσσῃ",
      "correct": "βδελύσσῃς",
      "severity": "grammatical",
      "category": "missing-letter",
      "confidence": "high",
      "note": "Final sigma is present in the printed form.",
      "_tier": "grammatical"
    },
    {
      "section": "BODY",
      "location": "Wis 11:19",
      "current": "ἠδύνατο συντρίψαι αὐτούς,",
      "correct": "ἠδύνατο συνεκτρῖψαι αὐτούς,",
      "severity": "meaning-altering",
      "category": "missing-prefix",
      "confidence": "high",
      "note": "Printed text reads συνεκτρῖψαι, not συντρίψαι.",
      "_tier": "body-meaning"
    },
    {
      "section": "BODY",
      "location": "Wis 12:4",
      "current": "ἔχλιστα",
      "correct": "ἔχθιστα",
      "severity": "meaning-altering",
      "category": "missing-letter",
      "confidence": "high",
      "note": "Theta omitted in transcript.",
      "_tier": "body-meaning"
    }
  ],
  "deferred": []
}