{
  "chapter": 75,
  "reference": "2 Baruch 75",
  "source_pdf_pages": [
    179
  ],
  "source_printed_pages": [
    163
  ],
  "chapter_bucket_method": "tentative_page_interpolation_v1",
  "overlap_expected": true,
  "source_text": "# Source page p0179 (printed 163)\n堋堀軖塥 堋堀軡堍軜軛軡 軖軞虉軟軛軔.\n堋軟軤 軛軤軡堍 軡墁軡塥軔軡墁\n軞塬軡軖 軛軜軔 軖軛軜堞軣軛軜堍\n軙軖堍軡堍塬軔 軜堍軙虉軡軔軡堍 軞軜虉軖軔\n堋堍 軖堀軙軔 軜堍堠虉堞軡堍 軤軖堍虉軡\n軔堍塬軔. 軜軔埽堞軡堠 軜軙虉堋軜堀軔\n堍堞堠軡堍 堋堍 堍堠虉軖軡軛軜堍\n軔軡軣 軙堍墁墁軖堀軜堍 堀堋軤軜軛輬軡.\n軜虉堍塬軔 軛堍軡堍 軛軜軡\n軤軔 堍軛軜軔 軤軛軡堍 軣軔軖軔\n堋軙堋 軙軡虉軤軙堍. 軜軤軔 堍塬墁堍堠堍\n堋軙堋 軙軡虉軛軖堍 堞軔塥虉軔\n軙堋塥軖堀軔 軡軛輬軡軖 軛軜軔\n軖軛軜堍 軡軜堠虉塥軔. 軤軔\n堍軤軙堍 軞軡軜虉墁軔. 軜軤軔\n堍軖埽堋軜堍 軔軡軤軡堍 軙軖堍軡堍. 堋堍\n堍堞堠軜軛軡 軗軡塥 堍軜虉堞軞軡\n塥虉軜軞軡堍 軖軖虉堍軡軔. 堀堋\n軔軡軤軡堍 軙軖堀軡軙軡堍 軤軛軡堍\n軖堍軡堍軔 埽軗軡軔軔. 堋埽軜軣軔\n軙軝軖堍軔 軛虈軜 軡軜堋堍軡軔 軛軜\n軙塬塥軡塥 軙堋墁軞軖軤軔. 軜堍塬軔\n軙塬塥軡塥 軙軤軔 堋墁軞軖軤軔.\n堋軟軤 軛堍軔 軛軤軡堍 軙堋虉堠軙堋堍\n軝軖堍軡堍 軖軛 軛虉軜軡.\n堋軟軤 軛堍軔 塥軞軡堠 軛軜\n軣軤 堀堍軡堍軔. 軜堠塥軡軖 軛軜\n軝堍軡堍 塬虉軖堀軔 堍軜軛塥軔\n軔軞塥堍軔 軙軔墁軜 堋堍 軣軔墁\n堠虉軙堋軡軔 軜堠虉塄軡軔 軔軞塥虉堍軡墁軔.\n軜軤軡墁 軔軜塥軞軔. 堋軙堋\n軙軔墁軡軙堀 堋塥軡軔 軖堀軜堠軖塥軛.\n軤軔 軗軡塥 堋墁軙塥軣軔. 軔軜\n堋軙堋 軙軖塄軔 塥虉堀軡堍軡 軔堍塬軔\n軙軤軔 堋埽墁軡軣軡堍. 軔軜 堋軙堋\n軙塄虈軔塥 埽軜軣軤軔 軙堀軡塥虉軔. 軔軜\n堋軙堋 堋蹋軙軔 軙堍軜塥軔\n堋軞虉塬軖墁軔 軜堋虈軙軖塥. 軔軜\n堋軙堋 堋堍 堀軖虉軙軔 堍堞軜塄\n軙軔軔塥 軖軜軞堍軡堍. 軔軤軔\n軤堍 軛軜虈 軙軔軡墁 堋墁墁軞堋軔\n軔堍墁 軜堋軞軜軡 軔堍墁\n軖堀軖虉軙軡軜軛軡. 堋軟軤 軙軔堍\n堋墁墁軞堋軜堍 軤軔 堋墁墁軞堋\n軔堍墁 軤軔 軖軞虉軡軜軛軡 軔堍塬軡堍\n軙軔軡軤軡堍 軙堋堍軡堍 軤軔 堋塬軣軞軡堍\n軙堍埽堠軜堍 軖軜軞堍軡堍. 軔軤軔\n軔堍塬軡堍 軙堋軣軡堍 堋軞塬虉軖墁軔\n堋塬軣軞軡堍 軙堍墁塥塄軜堍. 軞堍堍\n軙軡堍 軔堍塬軡堍"
}
