{
  "line_id": "line_05",
  "page": 42,
  "box_px": [
    179,
    611,
    966,
    650
  ],
  "box_pct": [
    0.07449,
    0.198184,
    0.401998,
    0.210834
  ],
  "finish_reason": "STOP",
  "usage": {
    "promptTokenCount": 335,
    "candidatesTokenCount": 21,
    "totalTokenCount": 630,
    "promptTokensDetails": [
      {
        "modality": "TEXT",
        "tokenCount": 77
      },
      {
        "modality": "IMAGE",
        "tokenCount": 258
      }
    ],
    "thoughtsTokenCount": 274
  },
  "chars": 23,
  "generated_at": "2026-04-21T20:46:38Z"
}
